termtype-1.0.4.dist-info/DESCRIPTION.rst
termtype-1.0.4.dist-info/METADATA
termtype-1.0.4.dist-info/RECORD
termtype-1.0.4.dist-info/WHEEL
termtype-1.0.4.dist-info/entry_points.txt
termtype-1.0.4.dist-info/metadata.json
termtype-1.0.4.dist-info/top_level.txt
termtypelib/__init__.py
