Metadata-Version: 2.0
Name: termtype
Version: 1.0.4
Summary: A simple tool to simulate typing in a terminal.
Home-page: https://github.com/hypothesist/termtype
Author: Adhityaa Chandrasekar
Author-email: c.adhityaa@gmail.com
License: GNU GPLv3
Keywords: terminal type simulate automatic text xdotool
Platform: UNKNOWN
Classifier: Development Status :: 5 - Production/Stable
Classifier: Intended Audience :: End Users/Desktop
Classifier: Topic :: Utilities
Classifier: Programming Language :: Python :: 2
Classifier: Programming Language :: Python :: 2.6
Classifier: Programming Language :: Python :: 2.7
Classifier: Programming Language :: Python :: 3
Classifier: Programming Language :: Python :: 3.2
Classifier: Programming Language :: Python :: 3.3
Classifier: Programming Language :: Python :: 3.4
Classifier: Programming Language :: Python :: 3.5
Classifier: Operating System :: OS Independent
